{
    "approval": {
        "date": "2020-05-12T21:30:35.802357+00:00",
        "user": {
            "display_name": "Ariel Schvartz",
            "uuid": "{5c836730-a9fb-4e6a-a4d8-95134d170b99}",
            "links": {
                "self": {
                    "href": "https://api.bitbucket.org/2.0/users/%7B5c836730-a9fb-4e6a-a4d8-95134d170b99%7D"
                },
                "html": {
                    "href": "https://bitbucket.org/%7B5c836730-a9fb-4e6a-a4d8-95134d170b99%7D/"
                },
                "avatar": {
                    "href": "https://avatar-management--avatars.us-west-2.prod.public.atl-paas.net/557058:197d740a-7b53-4371-84af-97ce2224d812/510e51b6-f43a-40e9-b163-f047f86fbc45/128"
                }
            },
            "nickname": "Ariel Schvartz",
            "type": "user",
            "account_id": "557058:197d740a-7b53-4371-84af-97ce2224d812"
        }
    },
    "pullrequest": {
        "rendered": {
            "description": {
                "raw": "* LAW-372 configure backend to delete task\r\n* LAW-372 add trigger to avoid updates on tasks marked as deleted\r\n\r\n‌",
                "markup": "markdown",
                "html": "<ul>\n<li>LAW-372 configure backend to delete task</li>\n<li>LAW-372 add trigger to avoid updates on tasks marked as deleted</li>\n</ul>\n<p>‌</p>",
                "type": "rendered"
            },
            "title": {
                "raw": "LAW-372 permitir deletar uma task",
                "markup": "markdown",
                "html": "<p>LAW-372 permitir deletar uma task</p>",
                "type": "rendered"
            }
        },
        "type": "pullrequest",
        "description": "* LAW-372 configure backend to delete task\r\n* LAW-372 add trigger to avoid updates on tasks marked as deleted\r\n\r\n‌",
        "links": {
            "decline": {
                "href": "https://api.bitbucket.org/2.0/repositories/lawgile/lawgile-backend/pullrequests/59/decline"
            },
            "diffstat": {
                "href": "https://api.bitbucket.org/2.0/repositories/lawgile/lawgile-backend/diffstat/lawgile/lawgile-backend:a4606e4f1f50%0Dd0f8809f84ac?from_pullrequest_id=59"
            },
            "commits": {
                "href": "https://api.bitbucket.org/2.0/repositories/lawgile/lawgile-backend/pullrequests/59/commits"
            },
            "self": {
                "href": "https://api.bitbucket.org/2.0/repositories/lawgile/lawgile-backend/pullrequests/59"
            },
            "comments": {
                "href": "https://api.bitbucket.org/2.0/repositories/lawgile/lawgile-backend/pullrequests/59/comments"
            },
            "merge": {
                "href": "https://api.bitbucket.org/2.0/repositories/lawgile/lawgile-backend/pullrequests/59/merge"
            },
            "html": {
                "href": "https://bitbucket.org/lawgile/lawgile-backend/pull-requests/59"
            },
            "activity": {
                "href": "https://api.bitbucket.org/2.0/repositories/lawgile/lawgile-backend/pullrequests/59/activity"
            },
            "diff": {
                "href": "https://api.bitbucket.org/2.0/repositories/lawgile/lawgile-backend/diff/lawgile/lawgile-backend:a4606e4f1f50%0Dd0f8809f84ac?from_pullrequest_id=59"
            },
            "approve": {
                "href": "https://api.bitbucket.org/2.0/repositories/lawgile/lawgile-backend/pullrequests/59/approve"
            },
            "statuses": {
                "href": "https://api.bitbucket.org/2.0/repositories/lawgile/lawgile-backend/pullrequests/59/statuses"
            }
        },
        "title": "LAW-372 permitir deletar uma task",
        "close_source_branch": false,
        "reviewers": [
            {
                "display_name": "Igor Rocha",
                "uuid": "{54aeabc2-c2aa-4d4c-aa39-85027bbe321f}",
                "links": {
                    "self": {
                        "href": "https://api.bitbucket.org/2.0/users/%7B54aeabc2-c2aa-4d4c-aa39-85027bbe321f%7D"
                    },
                    "html": {
                        "href": "https://bitbucket.org/%7B54aeabc2-c2aa-4d4c-aa39-85027bbe321f%7D/"
                    },
                    "avatar": {
                        "href": "https://avatar-management--avatars.us-west-2.prod.public.atl-paas.net/5d2e49b1b7a11e0c7f31dae1/17075303-0398-471e-a60d-6f7bf84f492b/128"
                    }
                },
                "nickname": "Igor Rocha",
                "type": "user",
                "account_id": "5d2e49b1b7a11e0c7f31dae1"
            }
        ],
        "id": 59,
        "destination": {
            "commit": {
                "hash": "d0f8809f84ac",
                "type": "commit",
                "links": {
                    "self": {
                        "href": "https://api.bitbucket.org/2.0/repositories/lawgile/lawgile-backend/commit/d0f8809f84ac"
                    },
                    "html": {
                        "href": "https://bitbucket.org/lawgile/lawgile-backend/commits/d0f8809f84ac"
                    }
                }
            },
            "repository": {
                "links": {
                    "self": {
                        "href": "https://api.bitbucket.org/2.0/repositories/lawgile/lawgile-backend"
                    },
                    "html": {
                        "href": "https://bitbucket.org/lawgile/lawgile-backend"
                    },
                    "avatar": {
                        "href": "https://bytebucket.org/ravatar/%7B3f21281e-21b1-4600-a901-474f983a611b%7D?ts=default"
                    }
                },
                "type": "repository",
                "name": "lawgile-backend",
                "full_name": "lawgile/lawgile-backend",
                "uuid": "{3f21281e-21b1-4600-a901-474f983a611b}"
            },
            "branch": {
                "name": "master"
            }
        },
        "created_on": "2020-05-12T21:24:53.761322+00:00",
        "summary": {
            "raw": "* LAW-372 configure backend to delete task\r\n* LAW-372 add trigger to avoid updates on tasks marked as deleted\r\n\r\n‌",
            "markup": "markdown",
            "html": "<ul>\n<li>LAW-372 configure backend to delete task</li>\n<li>LAW-372 add trigger to avoid updates on tasks marked as deleted</li>\n</ul>\n<p>‌</p>",
            "type": "rendered"
        },
        "source": {
            "commit": {
                "hash": "a4606e4f1f50",
                "type": "commit",
                "links": {
                    "self": {
                        "href": "https://api.bitbucket.org/2.0/repositories/lawgile/lawgile-backend/commit/a4606e4f1f50"
                    },
                    "html": {
                        "href": "https://bitbucket.org/lawgile/lawgile-backend/commits/a4606e4f1f50"
                    }
                }
            },
            "repository": {
                "links": {
                    "self": {
                        "href": "https://api.bitbucket.org/2.0/repositories/lawgile/lawgile-backend"
                    },
                    "html": {
                        "href": "https://bitbucket.org/lawgile/lawgile-backend"
                    },
                    "avatar": {
                        "href": "https://bytebucket.org/ravatar/%7B3f21281e-21b1-4600-a901-474f983a611b%7D?ts=default"
                    }
                },
                "type": "repository",
                "name": "lawgile-backend",
                "full_name": "lawgile/lawgile-backend",
                "uuid": "{3f21281e-21b1-4600-a901-474f983a611b}"
            },
            "branch": {
                "name": "LAW-372-permitir-deletar-uma-task"
            }
        },
        "comment_count": 0,
        "state": "OPEN",
        "task_count": 0,
        "participants": [
            {
                "role": "REVIEWER",
                "participated_on": null,
                "type": "participant",
                "approved": false,
                "user": {
                    "display_name": "Igor Rocha",
                    "uuid": "{54aeabc2-c2aa-4d4c-aa39-85027bbe321f}",
                    "links": {
                        "self": {
                            "href": "https://api.bitbucket.org/2.0/users/%7B54aeabc2-c2aa-4d4c-aa39-85027bbe321f%7D"
                        },
                        "html": {
                            "href": "https://bitbucket.org/%7B54aeabc2-c2aa-4d4c-aa39-85027bbe321f%7D/"
                        },
                        "avatar": {
                            "href": "https://avatar-management--avatars.us-west-2.prod.public.atl-paas.net/5d2e49b1b7a11e0c7f31dae1/17075303-0398-471e-a60d-6f7bf84f492b/128"
                        }
                    },
                    "nickname": "Igor Rocha",
                    "type": "user",
                    "account_id": "5d2e49b1b7a11e0c7f31dae1"
                }
            },
            {
                "role": "PARTICIPANT",
                "participated_on": "2020-05-12T21:30:35.802357+00:00",
                "type": "participant",
                "approved": true,
                "user": {
                    "display_name": "Ariel Schvartz",
                    "uuid": "{5c836730-a9fb-4e6a-a4d8-95134d170b99}",
                    "links": {
                        "self": {
                            "href": "https://api.bitbucket.org/2.0/users/%7B5c836730-a9fb-4e6a-a4d8-95134d170b99%7D"
                        },
                        "html": {
                            "href": "https://bitbucket.org/%7B5c836730-a9fb-4e6a-a4d8-95134d170b99%7D/"
                        },
                        "avatar": {
                            "href": "https://avatar-management--avatars.us-west-2.prod.public.atl-paas.net/557058:197d740a-7b53-4371-84af-97ce2224d812/510e51b6-f43a-40e9-b163-f047f86fbc45/128"
                        }
                    },
                    "nickname": "Ariel Schvartz",
                    "type": "user",
                    "account_id": "557058:197d740a-7b53-4371-84af-97ce2224d812"
                }
            }
        ],
        "reason": "",
        "updated_on": "2020-05-12T21:30:35.802357+00:00",
        "author": {
            "display_name": "Ariel Schvartz",
            "uuid": "{5c836730-a9fb-4e6a-a4d8-95134d170b99}",
            "links": {
                "self": {
                    "href": "https://api.bitbucket.org/2.0/users/%7B5c836730-a9fb-4e6a-a4d8-95134d170b99%7D"
                },
                "html": {
                    "href": "https://bitbucket.org/%7B5c836730-a9fb-4e6a-a4d8-95134d170b99%7D/"
                },
                "avatar": {
                    "href": "https://avatar-management--avatars.us-west-2.prod.public.atl-paas.net/557058:197d740a-7b53-4371-84af-97ce2224d812/510e51b6-f43a-40e9-b163-f047f86fbc45/128"
                }
            },
            "nickname": "Ariel Schvartz",
            "type": "user",
            "account_id": "557058:197d740a-7b53-4371-84af-97ce2224d812"
        },
        "merge_commit": null,
        "closed_by": null
    },
    "repository": {
        "scm": "git",
        "website": "",
        "uuid": "{3f21281e-21b1-4600-a901-474f983a611b}",
        "links": {
            "self": {
                "href": "https://api.bitbucket.org/2.0/repositories/lawgile/lawgile-backend"
            },
            "html": {
                "href": "https://bitbucket.org/lawgile/lawgile-backend"
            },
            "avatar": {
                "href": "https://bytebucket.org/ravatar/%7B3f21281e-21b1-4600-a901-474f983a611b%7D?ts=default"
            }
        },
        "project": {
            "links": {
                "self": {
                    "href": "https://api.bitbucket.org/2.0/workspaces/lawgile/projects/LAW"
                },
                "html": {
                    "href": "https://bitbucket.org/lawgile/workspace/projects/LAW"
                },
                "avatar": {
                    "href": "https://bitbucket.org/account/user/lawgile/projects/LAW/avatar/32?ts=1569597126"
                }
            },
            "type": "project",
            "name": "Lawgile WebApp",
            "key": "LAW",
            "uuid": "{bb592ee9-6267-415b-9bf6-c8edff897891}"
        },
        "full_name": "lawgile/lawgile-backend",
        "owner": {
            "username": "lawgile",
            "display_name": "Lawgile",
            "type": "team",
            "uuid": "{5f7d3d5d-4e85-4c2a-a938-0eaeba837405}",
            "links": {
                "self": {
                    "href": "https://api.bitbucket.org/2.0/teams/%7B5f7d3d5d-4e85-4c2a-a938-0eaeba837405%7D"
                },
                "html": {
                    "href": "https://bitbucket.org/%7B5f7d3d5d-4e85-4c2a-a938-0eaeba837405%7D/"
                },
                "avatar": {
                    "href": "https://bitbucket.org/account/lawgile/avatar/"
                }
            }
        },
        "type": "repository",
        "is_private": true,
        "name": "lawgile-backend"
    },
    "actor": {
        "display_name": "Ariel Schvartz",
        "uuid": "{5c836730-a9fb-4e6a-a4d8-95134d170b99}",
        "links": {
            "self": {
                "href": "https://api.bitbucket.org/2.0/users/%7B5c836730-a9fb-4e6a-a4d8-95134d170b99%7D"
            },
            "html": {
                "href": "https://bitbucket.org/%7B5c836730-a9fb-4e6a-a4d8-95134d170b99%7D/"
            },
            "avatar": {
                "href": "https://avatar-management--avatars.us-west-2.prod.public.atl-paas.net/557058:197d740a-7b53-4371-84af-97ce2224d812/510e51b6-f43a-40e9-b163-f047f86fbc45/128"
            }
        },
        "nickname": "Ariel Schvartz",
        "type": "user",
        "account_id": "557058:197d740a-7b53-4371-84af-97ce2224d812"
    }
}